{"id":"n0","children":[{"id":"default","labels":[{"text":"Default","x":0.0,"y":0.0,"width":43.0,"height":15.0}],"children":[{"id":"n1","labels":[{"text":"1","x":0.0,"y":0.0,"width":0.0,"height":0.0}],"ports":[{"id":"p1","layoutOptions":{"org.eclipse.elk.port.side":"EAST","org.eclipse.elk.port.index":"0"},"x":0.0,"y":0.0,"width":0.0,"height":0.0},{"id":"p2","layoutOptions":{"org.eclipse.elk.port.side":"EAST","org.eclipse.elk.port.index":"1"},"x":0.0,"y":0.0,"width":0.0,"height":0.0}],"layoutOptions":{"org.eclipse.elk.portConstraints":"FIXED_ORDER"},"x":0.0,"y":0.0,"width":0.0,"height":0.0},{"id":"n2","labels":[{"text":"2","x":0.0,"y":0.0,"width":0.0,"height":0.0}],"x":0.0,"y":0.0,"width":0.0,"height":0.0},{"id":"n3","labels":[{"text":"3","x":0.0,"y":0.0,"width":0.0,"height":0.0}],"x":0.0,"y":0.0,"width":0.0,"height":0.0}],"layoutOptions":{"org.eclipse.elk.algorithm":"layered","org.eclipse.elk.nodeLabels.placement":"[H_CENTER, V_TOP, INSIDE]"},"x":0.0,"y":0.0,"width":0.0,"height":0.0,"edges":[{"id":"e0","sources":["p1"],"targets":["n2"]},{"id":"e1","sources":["p2"],"targets":["n3"]}]},{"id":"semiInteractive","labels":[{"text":"Semi-Interactive","x":0.0,"y":0.0,"width":97.0,"height":15.0}],"children":[{"id":"n1_g330102","labels":[{"text":"1","x":0.0,"y":0.0,"width":0.0,"height":0.0}],"ports":[{"id":"p1_g255380","layoutOptions":{"org.eclipse.elk.port.side":"EAST","org.eclipse.elk.port.index":"0"},"x":0.0,"y":0.0,"width":0.0,"height":0.0},{"id":"p2_g963314","layoutOptions":{"org.eclipse.elk.port.side":"EAST","org.eclipse.elk.port.index":"1"},"x":0.0,"y":0.0,"width":0.0,"height":0.0}],"layoutOptions":{"org.eclipse.elk.portConstraints":"FIXED_ORDER"},"x":0.0,"y":0.0,"width":0.0,"height":0.0},{"id":"n2_g610238","labels":[{"text":"2","x":0.0,"y":0.0,"width":0.0,"height":0.0}],"layoutOptions":{"org.eclipse.elk.position":"(0.0,100.0)"},"x":0.0,"y":0.0,"width":0.0,"height":0.0},{"id":"n3_g416741","labels":[{"text":"3","x":0.0,"y":0.0,"width":0.0,"height":0.0}],"layoutOptions":{"org.eclipse.elk.position":"(0.0,0.0)"},"x":0.0,"y":0.0,"width":0.0,"height":0.0}],"layoutOptions":{"org.eclipse.elk.algorithm":"layered","org.eclipse.elk.nodeLabels.placement":"[H_CENTER, V_TOP, INSIDE]","org.eclipse.elk.layered.crossingMinimization.semiInteractive":"true"},"x":0.0,"y":0.0,"width":0.0,"height":0.0,"edges":[{"id":"e2","sources":["p1_g255380"],"targets":["n2_g610238"]},{"id":"e3","sources":["p2_g963314"],"targets":["n3_g416741"]}]},{"id":"interactive","labels":[{"text":"Interactive","x":0.0,"y":0.0,"width":58.0,"height":15.0}],"children":[{"id":"n1_g097407","labels":[{"text":"1","x":0.0,"y":0.0,"width":0.0,"height":0.0}],"ports":[{"id":"p1_g903478","layoutOptions":{"org.eclipse.elk.port.side":"EAST","org.eclipse.elk.port.index":"0"},"x":0.0,"y":0.0,"width":0.0,"height":0.0},{"id":"p2_g769190","layoutOptions":{"org.eclipse.elk.port.side":"EAST","org.eclipse.elk.port.index":"1"},"x":0.0,"y":0.0,"width":0.0,"height":0.0}],"layoutOptions":{"org.eclipse.elk.portConstraints":"FIXED_ORDER"},"x":0.0,"y":0.0,"width":0.0,"height":0.0},{"id":"n2_g992149","labels":[{"text":"2","x":0.0,"y":0.0,"width":0.0,"height":0.0}],"x":0.0,"y":100.0,"width":0.0,"height":0.0},{"id":"n3_g617426","labels":[{"text":"3","x":0.0,"y":0.0,"width":0.0,"height":0.0}],"x":0.0,"y":0.0,"width":0.0,"height":0.0}],"layoutOptions":{"org.eclipse.elk.algorithm":"layered","org.eclipse.elk.nodeSize.constraints":"[NODE_LABELS]","org.eclipse.elk.layered.crossingMinimization.strategy":"INTERACTIVE","org.eclipse.elk.nodeLabels.placement":"[H_CENTER, V_TOP, INSIDE]"},"x":0.0,"y":0.0,"width":0.0,"height":0.0,"edges":[{"id":"e4","sources":["p1_g903478"],"targets":["n2_g992149"]},{"id":"e5","sources":["p2_g769190"],"targets":["n3_g617426"]}]}],"layoutOptions":{"org.eclipse.elk.aspectRatio":"0.1","org.eclipse.elk.randomSeed":"1"},"x":0.0,"y":0.0,"width":0.0,"height":0.0}