{"children":[{"height":41,"id":"N1","labels":[{"height":15,"id":"L1","text":"DataReceived","width":80,"x":0,"y":-20}],"layoutOptions":{"org.eclipse.elk.nodeLabels.placement":"[H_LEFT, V_TOP, OUTSIDE]","org.eclipse.elk.portConstraints":"FIXED_ORDER"},"ports":[{"height":8,"id":"P1","layoutOptions":{"org.eclipse.elk.port.index":"0","org.eclipse.elk.port.side":"EAST"},"width":8,"x":61,"y":16.5},{"height":8,"id":"P2","layoutOptions":{"org.eclipse.elk.port.index":"-1","org.eclipse.elk.port.side":"WEST"},"width":8,"x":-8,"y":8.333333333333334},{"height":8,"id":"P3","layoutOptions":{"org.eclipse.elk.port.index":"-2","org.eclipse.elk.port.side":"WEST"},"width":8,"x":-8,"y":24.66666666666667}],"width":61,"x":20,"y":269.0833333333333},{"height":40,"id":"N2","labels":[{"height":15,"id":"L2","text":"MonitorValue - q1 length","width":141,"x":0,"y":-20}],"layoutOptions":{"org.eclipse.elk.nodeLabels.placement":"[H_LEFT, V_TOP, OUTSIDE]","org.eclipse.elk.portConstraints":"FIXED_ORDER"},"ports":[{"height":8,"id":"P4","layoutOptions":{"org.eclipse.elk.port.index":"0","org.eclipse.elk.port.side":"WEST"},"width":8,"x":-8,"y":16}],"width":60,"x":332,"y":32},{"height":40,"id":"N3","labels":[{"height":15,"id":"L3","text":"MonitorValue - q2 length","width":141,"x":0,"y":-20}],"layoutOptions":{"org.eclipse.elk.nodeLabels.placement":"[H_LEFT, V_TOP, OUTSIDE]","org.eclipse.elk.portConstraints":"FIXED_ORDER"},"ports":[{"height":8,"id":"P5","layoutOptions":{"org.eclipse.elk.port.index":"0","org.eclipse.elk.port.side":"WEST"},"width":8,"x":-8,"y":16}],"width":60,"x":332,"y":290},{"height":31,"id":"N4","labels":[{"height":15,"id":"L4","text":"dropped","width":47,"x":0,"y":-20}],"layoutOptions":{"org.eclipse.elk.nodeLabels.placement":"[H_LEFT, V_TOP, OUTSIDE]","org.eclipse.elk.portConstraints":"FIXED_ORDER"},"ports":[{"height":8,"id":"P6","layoutOptions":{"org.eclipse.elk.port.index":"0","org.eclipse.elk.port.side":"WEST"},"width":8,"x":-8,"y":11.5}],"width":41,"x":235,"y":210.33333333333331},{"height":41,"id":"N5","labels":[{"height":15,"id":"L5","text":"Distributor","width":60,"x":0,"y":-20}],"layoutOptions":{"org.eclipse.elk.nodeLabels.placement":"[H_LEFT, V_TOP, OUTSIDE]","org.eclipse.elk.portConstraints":"FIXED_ORDER"},"ports":[{"height":8,"id":"P7","layoutOptions":{"org.eclipse.elk.port.index":"0","org.eclipse.elk.port.side":"WEST"},"width":8,"x":-8,"y":4.25},{"height":8,"id":"P8","layoutOptions":{"org.eclipse.elk.port.index":"-1","org.eclipse.elk.port.side":"WEST"},"width":8,"x":-8,"y":16.5},{"height":8,"id":"P9","layoutOptions":{"org.eclipse.elk.port.index":"-2","org.eclipse.elk.port.side":"WEST"},"width":8,"x":-8,"y":28.75},{"height":8,"id":"P10","layoutOptions":{"org.eclipse.elk.port.index":"3","org.eclipse.elk.port.side":"EAST"},"width":8,"x":61,"y":4.25},{"height":8,"id":"P11","layoutOptions":{"org.eclipse.elk.port.index":"4","org.eclipse.elk.port.side":"EAST"},"width":8,"x":61,"y":16.5},{"height":8,"id":"P12","layoutOptions":{"org.eclipse.elk.port.index":"5","org.eclipse.elk.port.side":"EAST"},"width":8,"x":61,"y":28.75}],"width":61,"x":128,"y":269.0833333333333},{"height":41,"id":"N6","labels":[{"height":15,"id":"L6","text":"Queue1","width":46,"x":0,"y":-20}],"layoutOptions":{"org.eclipse.elk.nodeLabels.placement":"[H_LEFT, V_TOP, OUTSIDE]","org.eclipse.elk.portConstraints":"FIXED_ORDER"},"ports":[{"height":8,"id":"P13","layoutOptions":{"org.eclipse.elk.port.index":"0","org.eclipse.elk.port.side":"WEST"},"width":8,"x":-8,"y":16.5},{"height":8,"id":"P14","layoutOptions":{"org.eclipse.elk.port.index":"1","org.eclipse.elk.port.side":"EAST"},"width":8,"x":61,"y":16.5},{"height":8,"id":"P15","layoutOptions":{"org.eclipse.elk.port.index":"2","org.eclipse.elk.port.side":"NORTH"},"width":8,"x":26.5,"y":-8}],"width":61,"x":235,"y":112},{"height":41,"id":"N7","labels":[{"height":15,"id":"L7","text":"Queue2","width":46,"x":0,"y":-20}],"layoutOptions":{"org.eclipse.elk.nodeLabels.placement":"[H_LEFT, V_TOP, OUTSIDE]","org.eclipse.elk.portConstraints":"FIXED_ORDER"},"ports":[{"height":8,"id":"P16","layoutOptions":{"org.eclipse.elk.port.index":"0","org.eclipse.elk.port.side":"WEST"},"width":8,"x":-8,"y":16.5},{"height":8,"id":"P17","layoutOptions":{"org.eclipse.elk.port.index":"1","org.eclipse.elk.port.side":"EAST"},"width":8,"x":61,"y":8.333333333333334},{"height":8,"id":"P18","layoutOptions":{"org.eclipse.elk.port.index":"2","org.eclipse.elk.port.side":"EAST"},"width":8,"x":61,"y":24.66666666666667}],"width":61,"x":235,"y":281.3333333333333},{"height":41,"id":"N8","labels":[{"height":15,"id":"L8","text":"Counter","width":46,"x":0,"y":-20}],"layoutOptions":{"org.eclipse.elk.nodeLabels.placement":"[H_LEFT, V_TOP, OUTSIDE]","org.eclipse.elk.portConstraints":"FIXED_ORDER"},"ports":[{"height":8,"id":"P19","layoutOptions":{"org.eclipse.elk.port.index":"0","org.eclipse.elk.port.side":"WEST"},"width":8,"x":-8,"y":8.333333333333334},{"height":8,"id":"P20","layoutOptions":{"org.eclipse.elk.port.index":"-1","org.eclipse.elk.port.side":"WEST"},"width":8,"x":-8,"y":24.66666666666667},{"height":8,"id":"P21","layoutOptions":{"org.eclipse.elk.port.index":"2","org.eclipse.elk.port.side":"EAST"},"width":8,"x":61,"y":16.5}],"width":61,"x":501,"y":120.16666666666669},{"height":41,"id":"N9","labels":[{"height":15,"id":"L9","text":"RecordAssembler","width":104,"x":0,"y":-20}],"layoutOptions":{"org.eclipse.elk.nodeLabels.placement":"[H_LEFT, V_TOP, OUTSIDE]","org.eclipse.elk.portConstraints":"FIXED_ORDER"},"ports":[{"height":8,"id":"P22","layoutOptions":{"org.eclipse.elk.port.index":"0","org.eclipse.elk.port.side":"EAST"},"width":8,"x":10,"y":16.5},{"height":8,"id":"P23","layoutOptions":{"org.eclipse.elk.port.index":"-1","org.eclipse.elk.port.side":"WEST"},"width":8,"x":-8,"y":8.333333333333334},{"height":8,"id":"P24","layoutOptions":{"org.eclipse.elk.port.index":"-2","org.eclipse.elk.port.side":"WEST"},"width":8,"x":-8,"y":24.66666666666667}],"width":10,"x":598,"y":112},{"height":31,"id":"N10","labels":[{"height":15,"id":"L10","text":"Display","width":43,"x":0,"y":-20}],"layoutOptions":{"org.eclipse.elk.nodeLabels.placement":"[H_LEFT, V_TOP, OUTSIDE]","org.eclipse.elk.portConstraints":"FIXED_ORDER"},"ports":[{"height":8,"id":"P25","layoutOptions":{"org.eclipse.elk.port.index":"0","org.eclipse.elk.port.side":"WEST"},"width":8,"x":-8,"y":11.5}],"width":41,"x":730,"y":117},{"height":41,"id":"N11","labels":[{"height":15,"id":"L11","text":"Counter","width":46,"x":0,"y":-20}],"layoutOptions":{"org.eclipse.elk.nodeLabels.placement":"[H_LEFT, V_TOP, OUTSIDE]","org.eclipse.elk.portConstraints":"FIXED_ORDER"},"ports":[{"height":8,"id":"P26","layoutOptions":{"org.eclipse.elk.port.index":"0","org.eclipse.elk.port.side":"WEST"},"width":8,"x":-8,"y":8.333333333333334},{"height":8,"id":"P27","layoutOptions":{"org.eclipse.elk.port.index":"-1","org.eclipse.elk.port.side":"WEST"},"width":8,"x":-8,"y":24.66666666666667},{"height":8,"id":"P28","layoutOptions":{"org.eclipse.elk.port.index":"2","org.eclipse.elk.port.side":"EAST"},"width":8,"x":61,"y":16.5}],"width":61,"x":501,"y":209.16666666666669},{"height":41,"id":"N12","labels":[{"height":15,"id":"L12","text":"RecordAssembler","width":104,"x":0,"y":-20}],"layoutOptions":{"org.eclipse.elk.nodeLabels.placement":"[H_LEFT, V_TOP, OUTSIDE]","org.eclipse.elk.portConstraints":"FIXED_ORDER"},"ports":[{"height":8,"id":"P29","layoutOptions":{"org.eclipse.elk.port.index":"0","org.eclipse.elk.port.side":"EAST"},"width":8,"x":10,"y":16.5},{"height":8,"id":"P30","layoutOptions":{"org.eclipse.elk.port.index":"-1","org.eclipse.elk.port.side":"WEST"},"width":8,"x":-8,"y":8.333333333333334},{"height":8,"id":"P31","layoutOptions":{"org.eclipse.elk.port.index":"-2","org.eclipse.elk.port.side":"WEST"},"width":8,"x":-8,"y":24.66666666666667}],"width":10,"x":598,"y":201},{"height":31,"id":"N13","labels":[{"height":15,"id":"L13","text":"Display","width":43,"x":0,"y":-20}],"layoutOptions":{"org.eclipse.elk.nodeLabels.placement":"[H_LEFT, V_TOP, OUTSIDE]","org.eclipse.elk.portConstraints":"FIXED_ORDER"},"ports":[{"height":8,"id":"P32","layoutOptions":{"org.eclipse.elk.port.index":"0","org.eclipse.elk.port.side":"WEST"},"width":8,"x":-8,"y":11.5}],"width":41,"x":730,"y":206},{"height":41,"id":"N14","labels":[{"height":15,"id":"L14","text":"Sleep","width":34,"x":0,"y":-20}],"layoutOptions":{"org.eclipse.elk.nodeLabels.placement":"[H_LEFT, V_TOP, OUTSIDE]","org.eclipse.elk.portConstraints":"FIXED_ORDER"},"ports":[{"height":8,"id":"P33","layoutOptions":{"org.eclipse.elk.port.index":"0","org.eclipse.elk.port.side":"WEST"},"width":8,"x":-8,"y":16.5},{"height":8,"id":"P34","layoutOptions":{"org.eclipse.elk.port.index":"1","org.eclipse.elk.port.side":"EAST"},"width":8,"x":61,"y":16.5},{"height":8,"id":"P35","layoutOptions":{"org.eclipse.elk.port.index":"-2","org.eclipse.elk.port.side":"SOUTH"},"width":8,"x":26.5,"y":41}],"width":61,"x":368,"y":112},{"height":41,"id":"N15","labels":[{"height":15,"id":"L15","text":"Sleep","width":34,"x":0,"y":-20}],"layoutOptions":{"org.eclipse.elk.nodeLabels.placement":"[H_LEFT, V_TOP, OUTSIDE]","org.eclipse.elk.portConstraints":"FIXED_ORDER"},"ports":[{"height":8,"id":"P36","layoutOptions":{"org.eclipse.elk.port.index":"0","org.eclipse.elk.port.side":"WEST"},"width":8,"x":-8,"y":16.5},{"height":8,"id":"P37","layoutOptions":{"org.eclipse.elk.port.index":"1","org.eclipse.elk.port.side":"EAST"},"width":8,"x":61,"y":16.5},{"height":8,"id":"P38","layoutOptions":{"org.eclipse.elk.port.index":"-2","org.eclipse.elk.port.side":"SOUTH"},"width":8,"x":26.5,"y":41}],"width":61,"x":368,"y":201}],"edges":[{"container":"G1","id":"E1","sections":[{"endPoint":{"x":120,"y":289.5833333333333},"id":"E1_s0","incomingShape":"P1","outgoingShape":"P8","startPoint":{"x":89,"y":289.5833333333333}}],"sources":["P1"],"targets":["P8"]},{"container":"G1","id":"E2","sections":[{"bendPoints":[{"x":217,"y":289.5833333333333},{"x":217,"y":225.83333333333331}],"endPoint":{"x":227,"y":225.83333333333331},"id":"E2_s0","incomingShape":"P11","outgoingShape":"P6","startPoint":{"x":197,"y":289.5833333333333}}],"sources":["P11"],"targets":["P6"]},{"container":"G1","id":"E3","sections":[{"endPoint":{"x":227,"y":301.8333333333333},"id":"E3_s0","incomingShape":"P12","outgoingShape":"P16","startPoint":{"x":197,"y":301.8333333333333}}],"sources":["P12"],"targets":["P16"]},{"container":"G1","id":"E4","sections":[{"bendPoints":[{"x":207,"y":277.3333333333333},{"x":207,"y":132.5}],"endPoint":{"x":227,"y":132.5},"id":"E4_s0","incomingShape":"P10","outgoingShape":"P13","startPoint":{"x":197,"y":277.3333333333333}}],"sources":["P10"],"targets":["P13"]},{"container":"G1","id":"E5","junctionPoints":[{"x":265.5,"y":52}],"sections":[{"bendPoints":[{"x":265.5,"y":52}],"endPoint":{"x":324,"y":52},"id":"E5_s0","incomingShape":"P15","outgoingShape":"P4","startPoint":{"x":265.5,"y":104}}],"sources":["P15"],"targets":["P4"]},{"container":"G1","id":"E6","junctionPoints":[{"x":265.5,"y":52}],"sections":[{"bendPoints":[{"x":265.5,"y":52},{"x":110,"y":52},{"x":110,"y":277.3333333333333}],"endPoint":{"x":120,"y":277.3333333333333},"id":"E6_s0","incomingShape":"P15","outgoingShape":"P7","startPoint":{"x":265.5,"y":104}}],"sources":["P15"],"targets":["P7"]},{"container":"G1","id":"E7","sections":[{"endPoint":{"x":360,"y":132.5},"id":"E7_s0","incomingShape":"P14","outgoingShape":"P33","startPoint":{"x":304,"y":132.5}}],"sources":["P14"],"targets":["P33"]},{"container":"G1","id":"E8","sections":[{"endPoint":{"x":324,"y":310},"id":"E8_s0","incomingShape":"P18","outgoingShape":"P5","startPoint":{"x":304,"y":310}}],"sources":["P18"],"targets":["P5"]},{"container":"G1","id":"E9","junctionPoints":[{"x":314,"y":310}],"sections":[{"bendPoints":[{"x":314,"y":310},{"x":314,"y":332.3333333333333},{"x":110,"y":332.3333333333333},{"x":110,"y":301.8333333333333}],"endPoint":{"x":120,"y":301.8333333333333},"id":"E9_s0","incomingShape":"P18","outgoingShape":"P9","startPoint":{"x":304,"y":310}}],"sources":["P18"],"targets":["P9"]},{"container":"G1","id":"E10","sections":[{"bendPoints":[{"x":314,"y":293.66666666666663},{"x":314,"y":221.5}],"endPoint":{"x":360,"y":221.5},"id":"E10_s0","incomingShape":"P17","outgoingShape":"P36","startPoint":{"x":304,"y":293.66666666666663}}],"sources":["P17"],"targets":["P36"]},{"container":"G1","id":"E11","sections":[{"endPoint":{"x":590,"y":140.66666666666669},"id":"E11_s0","incomingShape":"P21","outgoingShape":"P24","startPoint":{"x":570,"y":140.66666666666669}}],"sources":["P21"],"targets":["P24"]},{"container":"G1","id":"E12","sections":[{"endPoint":{"x":722,"y":132.5},"id":"E12_s0","incomingShape":"P22","outgoingShape":"P25","startPoint":{"x":616,"y":132.5}}],"sources":["P22"],"targets":["P25"]},{"container":"G1","id":"E13","sections":[{"endPoint":{"x":590,"y":229.66666666666669},"id":"E13_s0","incomingShape":"P28","outgoingShape":"P31","startPoint":{"x":570,"y":229.66666666666669}}],"sources":["P28"],"targets":["P31"]},{"container":"G1","id":"E14","sections":[{"endPoint":{"x":722,"y":221.5},"id":"E14_s0","incomingShape":"P29","outgoingShape":"P32","startPoint":{"x":616,"y":221.5}}],"sources":["P29"],"targets":["P32"]},{"container":"G1","id":"E15","sections":[{"endPoint":{"x":493,"y":132.50000000000003},"id":"E15_s0","incomingShape":"P34","outgoingShape":"P19","startPoint":{"x":437,"y":132.5}}],"sources":["P34"],"targets":["P19"]},{"container":"G1","id":"E16","junctionPoints":[{"x":483,"y":132.5}],"sections":[{"bendPoints":[{"x":483,"y":132.5},{"x":483,"y":89.16666666666669},{"x":580,"y":89.16666666666669},{"x":580,"y":124.33333333333334}],"endPoint":{"x":590,"y":124.33333333333334},"id":"E16_s0","incomingShape":"P34","outgoingShape":"P23","startPoint":{"x":437,"y":132.5}}],"sources":["P34"],"targets":["P23"]},{"container":"G1","id":"E17","sections":[{"endPoint":{"x":493,"y":221.5},"id":"E17_s0","incomingShape":"P37","outgoingShape":"P26","startPoint":{"x":437,"y":221.5}}],"sources":["P37"],"targets":["P26"]},{"container":"G1","id":"E18","junctionPoints":[{"x":483,"y":221.5}],"sections":[{"bendPoints":[{"x":483,"y":221.5},{"x":483,"y":178.16666666666669},{"x":580,"y":178.16666666666669},{"x":580,"y":213.33333333333331}],"endPoint":{"x":590,"y":213.33333333333331},"id":"E18_s0","incomingShape":"P37","outgoingShape":"P30","startPoint":{"x":437,"y":221.5}}],"sources":["P37"],"targets":["P30"]}],"height":344.3333333333333,"id":"G1","layoutOptions":{"org.eclipse.elk.portConstraints":"FREE","org.eclipse.elk.randomSeed":"1"},"width":785,"x":0,"y":0}