{"children":[{"children":[{"height":41.0,"id":"N2","labels":[{"height":15.0,"id":"L2","text":"AddSubtract","width":72.0,"x":0.0,"y":-20.0}],"layoutOptions":{"org.eclipse.elk.nodeLabels.placement":"[H_LEFT, V_TOP, OUTSIDE]","org.eclipse.elk.portConstraints":"FIXED_ORDER"},"ports":[{"height":8.0,"id":"P3","layoutOptions":{"org.eclipse.elk.port.index":"0","org.eclipse.elk.port.side":"WEST"},"width":8.0,"x":-8.0,"y":8.333333333333334},{"height":8.0,"id":"P4","layoutOptions":{"org.eclipse.elk.port.index":"-1","org.eclipse.elk.port.side":"WEST"},"width":8.0,"x":-8.0,"y":24.66666666666667},{"height":8.0,"id":"P5","layoutOptions":{"org.eclipse.elk.port.index":"2","org.eclipse.elk.port.side":"EAST"},"width":8.0,"x":41.0,"y":16.5}],"width":41.0,"x":258.0,"y":107.0},{"height":46.0,"id":"N3","labels":[{"height":15.0,"id":"L3","text":"Repeat","width":41.0,"x":0.0,"y":-20.0}],"layoutOptions":{"org.eclipse.elk.nodeLabels.placement":"[H_LEFT, V_TOP, OUTSIDE]","org.eclipse.elk.portConstraints":"FIXED_ORDER"},"ports":[{"height":8.0,"id":"P6","layoutOptions":{"org.eclipse.elk.port.index":"0","org.eclipse.elk.port.side":"WEST"},"width":8.0,"x":-8.0,"y":19.0},{"height":8.0,"id":"P7","layoutOptions":{"org.eclipse.elk.port.index":"1","org.eclipse.elk.port.side":"EAST"},"width":8.0,"x":66.0,"y":19.0}],"width":66.0,"x":141.5,"y":118.0},{"height":46.0,"id":"N4","labels":[{"height":15.0,"id":"L4","text":"ArrayToSequence","width":103.0,"x":0.0,"y":-20.0}],"layoutOptions":{"org.eclipse.elk.nodeLabels.placement":"[H_LEFT, V_TOP, OUTSIDE]","org.eclipse.elk.portConstraints":"FIXED_ORDER"},"ports":[{"height":8.0,"id":"P8","layoutOptions":{"org.eclipse.elk.port.index":"0","org.eclipse.elk.port.side":"WEST"},"width":8.0,"x":-8.0,"y":19.0},{"height":8.0,"id":"P9","layoutOptions":{"org.eclipse.elk.port.index":"1","org.eclipse.elk.port.side":"EAST"},"width":8.0,"x":66.0,"y":19.0}],"width":66.0,"x":127.0,"y":32.0},{"height":25.0,"id":"N5","labels":[{"height":15.0,"id":"L5","text":"Expression","width":66.0,"x":0.0,"y":-20.0}],"layoutOptions":{"org.eclipse.elk.nodeLabels.placement":"[H_LEFT, V_TOP, OUTSIDE]","org.eclipse.elk.portConstraints":"FIXED_ORDER"},"ports":[{"height":8.0,"id":"P10","layoutOptions":{"org.eclipse.elk.port.index":"0","org.eclipse.elk.port.side":"EAST"},"width":8.0,"x":99.0,"y":8.5},{"height":8.0,"id":"P11","layoutOptions":{"org.eclipse.elk.port.index":"-1","org.eclipse.elk.port.side":"WEST"},"width":8.0,"x":-8.0,"y":8.5}],"width":99.0,"x":358.0,"y":115.08333333333334},{"height":25.0,"id":"N6","labels":[{"height":15.0,"id":"L6","text":"Expression3","width":73.0,"x":0.0,"y":-20.0}],"layoutOptions":{"org.eclipse.elk.nodeLabels.placement":"[H_LEFT, V_TOP, OUTSIDE]","org.eclipse.elk.portConstraints":"FIXED_ORDER"},"ports":[{"height":8.0,"id":"P12","layoutOptions":{"org.eclipse.elk.port.index":"0","org.eclipse.elk.port.side":"EAST"},"width":8.0,"x":158.0,"y":8.5},{"height":8.0,"id":"P13","layoutOptions":{"org.eclipse.elk.port.index":"-1","org.eclipse.elk.port.side":"WEST"},"width":8.0,"x":-8.0,"y":8.5}],"width":158.0,"x":493.0,"y":115.08333333333334},{"height":46.0,"id":"N7","labels":[{"height":15.0,"id":"L7","text":"FIR","width":21.0,"x":0.0,"y":-20.0}],"layoutOptions":{"org.eclipse.elk.nodeLabels.placement":"[H_LEFT, V_TOP, OUTSIDE]","org.eclipse.elk.portConstraints":"FIXED_ORDER"},"ports":[{"height":8.0,"id":"P14","layoutOptions":{"org.eclipse.elk.port.index":"0","org.eclipse.elk.port.side":"WEST"},"width":8.0,"x":-8.0,"y":19.0},{"height":8.0,"id":"P15","layoutOptions":{"org.eclipse.elk.port.index":"1","org.eclipse.elk.port.side":"EAST"},"width":8.0,"x":66.0,"y":19.0}],"width":66.0,"x":795.0,"y":96.41666666666667},{"height":41.0,"id":"N8","labels":[{"height":15.0,"id":"L8","text":"MultiplyDivide","width":80.0,"x":0.0,"y":-20.0}],"layoutOptions":{"org.eclipse.elk.nodeLabels.placement":"[H_LEFT, V_TOP, OUTSIDE]","org.eclipse.elk.portConstraints":"FIXED_ORDER"},"ports":[{"height":8.0,"id":"P16","layoutOptions":{"org.eclipse.elk.port.index":"0","org.eclipse.elk.port.side":"WEST"},"width":8.0,"x":-8.0,"y":8.333333333333334},{"height":8.0,"id":"P17","layoutOptions":{"org.eclipse.elk.port.index":"-1","org.eclipse.elk.port.side":"WEST"},"width":8.0,"x":-8.0,"y":24.66666666666667},{"height":8.0,"id":"P18","layoutOptions":{"org.eclipse.elk.port.index":"2","org.eclipse.elk.port.side":"EAST"},"width":8.0,"x":41.0,"y":16.5}],"width":41.0,"x":687.0,"y":98.91666666666667},{"height":25.0,"id":"N9","labels":[{"height":15.0,"id":"L9","text":"SampleDelay","width":77.0,"x":0.0,"y":-20.0}],"layoutOptions":{"org.eclipse.elk.nodeLabels.placement":"[H_LEFT, V_TOP, OUTSIDE]","org.eclipse.elk.portConstraints":"FIXED_ORDER"},"ports":[{"height":8.0,"id":"P19","layoutOptions":{"org.eclipse.elk.port.index":"0","org.eclipse.elk.port.side":"WEST"},"width":8.0,"x":-8.0,"y":8.5},{"height":8.0,"id":"P20","layoutOptions":{"org.eclipse.elk.port.index":"1","org.eclipse.elk.port.side":"EAST"},"width":8.0,"x":162.0,"y":8.5}],"width":162.0,"x":897.0,"y":182.41666666666669},{"height":41.0,"id":"N10","labels":[{"height":15.0,"id":"L10","text":"AddSubtract2","width":80.0,"x":0.0,"y":-20.0}],"layoutOptions":{"org.eclipse.elk.nodeLabels.placement":"[H_LEFT, V_TOP, OUTSIDE]","org.eclipse.elk.portConstraints":"FIXED_ORDER"},"ports":[{"height":8.0,"id":"P21","layoutOptions":{"org.eclipse.elk.port.index":"0","org.eclipse.elk.port.side":"WEST"},"width":8.0,"x":-8.0,"y":8.333333333333334},{"height":8.0,"id":"P22","layoutOptions":{"org.eclipse.elk.port.index":"-1","org.eclipse.elk.port.side":"WEST"},"width":8.0,"x":-8.0,"y":24.66666666666667},{"height":8.0,"id":"P23","layoutOptions":{"org.eclipse.elk.port.index":"2","org.eclipse.elk.port.side":"EAST"},"width":8.0,"x":41.0,"y":16.5}],"width":41.0,"x":1095.0,"y":182.58333333333331},{"height":46.0,"id":"N11","labels":[{"height":15.0,"id":"L11","text":"Scale","width":34.0,"x":0.0,"y":-20.0}],"layoutOptions":{"org.eclipse.elk.nodeLabels.placement":"[H_LEFT, V_TOP, OUTSIDE]","org.eclipse.elk.portConstraints":"FIXED_ORDER"},"ports":[{"height":8.0,"id":"P24","layoutOptions":{"org.eclipse.elk.port.index":"0","org.eclipse.elk.port.side":"WEST"},"width":8.0,"x":-8.0,"y":19.0},{"height":8.0,"id":"P25","layoutOptions":{"org.eclipse.elk.port.index":"1","org.eclipse.elk.port.side":"EAST"},"width":8.0,"x":66.0,"y":19.0}],"width":66.0,"x":1098.0,"y":96.58333333333333},{"height":25.0,"id":"N12","labels":[{"height":15.0,"id":"L12","text":"SampleDelay2","width":85.0,"x":0.0,"y":-20.0}],"layoutOptions":{"org.eclipse.elk.nodeLabels.placement":"[H_LEFT, V_TOP, OUTSIDE]","org.eclipse.elk.portConstraints":"FIXED_ORDER"},"ports":[{"height":8.0,"id":"P26","layoutOptions":{"org.eclipse.elk.port.index":"0","org.eclipse.elk.port.side":"WEST"},"width":8.0,"x":-8.0,"y":8.5},{"height":8.0,"id":"P27","layoutOptions":{"org.eclipse.elk.port.index":"1","org.eclipse.elk.port.side":"EAST"},"width":8.0,"x":160.0,"y":8.5}],"width":160.0,"x":1311.0,"y":115.24999999999999},{"height":41.0,"id":"N13","labels":[{"height":15.0,"id":"L13","text":"AddSubtract3","width":80.0,"x":0.0,"y":-20.0}],"layoutOptions":{"org.eclipse.elk.nodeLabels.placement":"[H_LEFT, V_TOP, OUTSIDE]","org.eclipse.elk.portConstraints":"FIXED_ORDER"},"ports":[{"height":8.0,"id":"P28","layoutOptions":{"org.eclipse.elk.port.index":"0","org.eclipse.elk.port.side":"WEST"},"width":8.0,"x":-8.0,"y":8.333333333333334},{"height":8.0,"id":"P29","layoutOptions":{"org.eclipse.elk.port.index":"-1","org.eclipse.elk.port.side":"WEST"},"width":8.0,"x":-8.0,"y":24.66666666666667},{"height":8.0,"id":"P30","layoutOptions":{"org.eclipse.elk.port.index":"2","org.eclipse.elk.port.side":"EAST"},"width":8.0,"x":41.0,"y":16.5}],"width":41.0,"x":1203.0,"y":107.24999999999999},{"height":46.0,"id":"N14","labels":[{"height":15.0,"id":"L14","text":"Scale2","width":41.0,"x":0.0,"y":-20.0}],"layoutOptions":{"org.eclipse.elk.nodeLabels.placement":"[H_LEFT, V_TOP, OUTSIDE]","org.eclipse.elk.portConstraints":"FIXED_ORDER"},"ports":[{"height":8.0,"id":"P31","layoutOptions":{"org.eclipse.elk.port.index":"0","org.eclipse.elk.port.side":"WEST"},"width":8.0,"x":-8.0,"y":19.0},{"height":8.0,"id":"P32","layoutOptions":{"org.eclipse.elk.port.index":"1","org.eclipse.elk.port.side":"EAST"},"width":8.0,"x":66.0,"y":19.0}],"width":66.0,"x":945.0,"y":96.41666666666667},{"height":41.0,"id":"N15","labels":[{"height":15.0,"id":"L15","text":"ArrayElement","width":79.0,"x":0.0,"y":-20.0}],"layoutOptions":{"org.eclipse.elk.nodeLabels.placement":"[H_LEFT, V_TOP, OUTSIDE]","org.eclipse.elk.portConstraints":"FIXED_ORDER"},"ports":[{"height":8.0,"id":"P33","layoutOptions":{"org.eclipse.elk.port.index":"0","org.eclipse.elk.port.side":"WEST"},"width":8.0,"x":-8.0,"y":8.333333333333334},{"height":8.0,"id":"P34","layoutOptions":{"org.eclipse.elk.port.index":"1","org.eclipse.elk.port.side":"EAST"},"width":8.0,"x":61.0,"y":16.5},{"height":8.0,"id":"P35","layoutOptions":{"org.eclipse.elk.port.index":"-2","org.eclipse.elk.port.side":"WEST"},"width":8.0,"x":-8.0,"y":24.66666666666667}],"width":61.0,"x":20.0,"y":120.5}],"edges":[{"container":"N1","id":"E5","sources":["P1"],"targets":["P8"]},{"container":"N1","id":"E6","sources":["P1"],"targets":["P33"]},{"container":"N1","id":"E7","junctionPoints":[{"x":340.0,"y":127.5}],"sections":[{"bendPoints":[{"x":340.0,"y":127.5},{"x":340.0,"y":127.58333333333334}],"endPoint":{"x":350.0,"y":127.58333333333334},"id":"E7_s0","incomingShape":"P5","outgoingShape":"P11","startPoint":{"x":307.0,"y":127.5}}],"sources":["P5"],"targets":["P11"]},{"container":"N1","id":"E8","sections":[{"bendPoints":[{"x":340.0,"y":127.5},{"x":340.0,"y":84.08333333333333},{"x":669.0,"y":84.08333333333333},{"x":669.0,"y":111.25}],"endPoint":{"x":679.0,"y":111.25},"id":"E8_s0","incomingShape":"P5","outgoingShape":"P16","startPoint":{"x":307.0,"y":127.5}}],"sources":["P5"],"targets":["P16"]},{"container":"N1","id":"E9","sections":[{"bendPoints":[{"x":240.0,"y":141.0},{"x":240.0,"y":135.66666666666669}],"endPoint":{"x":250.0,"y":135.66666666666669},"id":"E9_s0","incomingShape":"P7","outgoingShape":"P4","startPoint":{"x":215.5,"y":141.0}}],"sources":["P7"],"targets":["P4"]},{"container":"N1","id":"E10","sections":[{"bendPoints":[{"x":240.0,"y":55.0},{"x":240.0,"y":119.33333333333333}],"endPoint":{"x":250.0,"y":119.33333333333333},"id":"E10_s0","incomingShape":"P9","outgoingShape":"P3","startPoint":{"x":201.0,"y":55.0}}],"sources":["P9"],"targets":["P3"]},{"container":"N1","id":"E11","sections":[{"endPoint":{"x":485.0,"y":127.58333333333334},"id":"E11_s0","incomingShape":"P10","outgoingShape":"P13","startPoint":{"x":465.0,"y":127.58333333333334}}],"sources":["P10"],"targets":["P13"]},{"container":"N1","id":"E12","sections":[{"endPoint":{"x":679.0,"y":127.58333333333334},"id":"E12_s0","incomingShape":"P12","outgoingShape":"P17","startPoint":{"x":659.0,"y":127.58333333333334}}],"sources":["P12"],"targets":["P17"]},{"container":"N1","id":"E13","sections":[{"endPoint":{"x":937.0,"y":119.41666666666667},"id":"E13_s0","incomingShape":"P15","outgoingShape":"P31","startPoint":{"x":869.0,"y":119.41666666666667}}],"sources":["P15"],"targets":["P31"]},{"container":"N1","id":"E14","sections":[{"endPoint":{"x":787.0,"y":119.41666666666667},"id":"E14_s0","incomingShape":"P18","outgoingShape":"P14","startPoint":{"x":736.0,"y":119.41666666666667}}],"sources":["P18"],"targets":["P14"]},{"container":"N1","id":"E15","sections":[{"endPoint":{"x":1087.0,"y":194.91666666666666},"id":"E15_s0","incomingShape":"P20","outgoingShape":"P21","startPoint":{"x":1067.0,"y":194.91666666666669}}],"sources":["P20"],"targets":["P21"]},{"container":"N1","id":"E16","junctionPoints":[{"x":1077.0,"y":119.58333333333333}],"sections":[{"bendPoints":[{"x":1077.0,"y":194.91666666666669},{"x":1077.0,"y":119.58333333333333}],"endPoint":{"x":1090.0,"y":119.58333333333333},"id":"E16_s0","incomingShape":"P20","outgoingShape":"P24","startPoint":{"x":1067.0,"y":194.91666666666669}}],"sources":["P20"],"targets":["P24"]},{"container":"N1","id":"E17","sections":[{"bendPoints":[{"x":1185.0,"y":203.08333333333331},{"x":1185.0,"y":233.58333333333331},{"x":879.0,"y":233.58333333333331},{"x":879.0,"y":194.91666666666669}],"endPoint":{"x":889.0,"y":194.91666666666669},"id":"E17_s0","incomingShape":"P23","outgoingShape":"P19","startPoint":{"x":1144.0,"y":203.08333333333331}}],"sources":["P23"],"targets":["P19"]},{"container":"N1","id":"E18","sections":[{"endPoint":{"x":1195.0,"y":119.58333333333331},"id":"E18_s0","incomingShape":"P25","outgoingShape":"P28","startPoint":{"x":1172.0,"y":119.58333333333333}}],"sources":["P25"],"targets":["P28"]},{"container":"N1","id":"E19","junctionPoints":[{"x":1185.0,"y":119.58333333333331}],"sections":[{"bendPoints":[{"x":1489.0,"y":127.74999999999999},{"x":1489.0,"y":158.25},{"x":1185.0,"y":158.25},{"x":1185.0,"y":119.58333333333331}],"endPoint":{"x":1195.0,"y":119.58333333333331},"id":"E19_s0","incomingShape":"P27","outgoingShape":"P28","startPoint":{"x":1479.0,"y":127.74999999999999}}],"sources":["P27"],"targets":["P28"]},{"container":"N1","id":"E20","sources":["P30"],"targets":["P2"]},{"container":"N1","id":"E21","sections":[{"endPoint":{"x":1303.0,"y":127.74999999999999},"id":"E21_s0","incomingShape":"P30","outgoingShape":"P26","startPoint":{"x":1252.0,"y":127.74999999999999}}],"sources":["P30"],"targets":["P26"]},{"container":"N1","id":"E22","junctionPoints":[{"x":1077.0,"y":194.91666666666669}],"sections":[{"bendPoints":[{"x":1077.0,"y":119.41666666666667},{"x":1077.0,"y":194.91666666666669}],"endPoint":{"x":1087.0,"y":194.91666666666666},"id":"E22_s0","incomingShape":"P32","outgoingShape":"P21","startPoint":{"x":1019.0,"y":119.41666666666667}}],"sources":["P32"],"targets":["P21"]},{"container":"N1","id":"E23","sections":[{"endPoint":{"x":133.5,"y":141.0},"id":"E23_s0","incomingShape":"P34","outgoingShape":"P6","startPoint":{"x":89.0,"y":141.0}}],"sources":["P34"],"targets":["P6"]}],"height":245.58333333333331,"id":"N1","labels":[{"height":15.0,"id":"L1","text":"BodyModels","width":72.0,"x":0.0,"y":-20.0}],"layoutOptions":{"org.eclipse.elk.nodeLabels.placement":"[H_LEFT, V_TOP, OUTSIDE]","org.eclipse.elk.portConstraints":"FREE"},"ports":[{"height":8.0,"id":"P1","layoutOptions":{"org.eclipse.elk.port.index":"0","org.eclipse.elk.port.side":"WEST"},"width":8.0,"x":1501.0,"y":76.52777777777777},{"height":8.0,"id":"P2","layoutOptions":{"org.eclipse.elk.port.index":"1","org.eclipse.elk.port.side":"EAST"},"width":8.0,"x":1501.0,"y":161.05555555555554}],"width":1501.0,"x":12.0,"y":32.0},{"height":25.0,"id":"N16","labels":[{"height":15.0,"id":"L16","text":"SampleDelay2","width":85.0,"x":0.0,"y":-20.0}],"layoutOptions":{"org.eclipse.elk.nodeLabels.placement":"[H_LEFT, V_TOP, OUTSIDE]","org.eclipse.elk.portConstraints":"FIXED_ORDER"},"ports":[{"height":8.0,"id":"P36","layoutOptions":{"org.eclipse.elk.port.index":"0","org.eclipse.elk.port.side":"WEST"},"width":8.0,"x":-8.0,"y":8.5},{"height":8.0,"id":"P37","layoutOptions":{"org.eclipse.elk.port.index":"1","org.eclipse.elk.port.side":"EAST"},"width":8.0,"x":103.0,"y":8.5}],"width":103.0,"x":1676.0,"y":184.55555555555554},{"children":[{"height":40.0,"id":"N18","labels":[{"height":15.0,"id":"L18","text":"ViewScreen3D","width":86.0,"x":0.0,"y":-20.0}],"layoutOptions":{"org.eclipse.elk.nodeLabels.placement":"[H_LEFT, V_TOP, OUTSIDE]","org.eclipse.elk.portConstraints":"FIXED_ORDER"},"ports":[{"height":8.0,"id":"P39","layoutOptions":{"org.eclipse.elk.port.index":"0","org.eclipse.elk.port.side":"WEST"},"width":8.0,"x":-8.0,"y":16.0}],"width":60.0,"x":514.0,"y":93.25},{"height":31.0,"id":"N19","labels":[{"height":15.0,"id":"L19","text":"ArrayToElements","width":99.0,"x":0.0,"y":-20.0}],"layoutOptions":{"org.eclipse.elk.nodeLabels.placement":"[H_LEFT, V_TOP, OUTSIDE]","org.eclipse.elk.portConstraints":"FIXED_ORDER"},"ports":[{"height":8.0,"id":"P40","layoutOptions":{"org.eclipse.elk.port.index":"0","org.eclipse.elk.port.side":"WEST"},"width":8.0,"x":-8.0,"y":11.5},{"height":8.0,"id":"P41","layoutOptions":{"org.eclipse.elk.port.index":"1","org.eclipse.elk.port.side":"EAST"},"width":8.0,"x":31.0,"y":11.5}],"width":31.0,"x":20.0,"y":97.75},{"children":[{"height":40.0,"id":"N21","labels":[{"height":15.0,"id":"L21","text":"Sphere3D","width":58.0,"x":0.0,"y":-20.0}],"layoutOptions":{"org.eclipse.elk.nodeLabels.placement":"[H_LEFT, V_TOP, OUTSIDE]","org.eclipse.elk.portConstraints":"FIXED_ORDER"},"ports":[{"height":8.0,"id":"P44","layoutOptions":{"org.eclipse.elk.port.index":"0","org.eclipse.elk.port.side":"EAST"},"width":8.0,"x":60.0,"y":16.0}],"width":60.0,"x":114.0,"y":32.0},{"height":40.0,"id":"N22","labels":[{"height":15.0,"id":"L22","text":"Translate3D","width":70.0,"x":0.0,"y":-20.0}],"layoutOptions":{"org.eclipse.elk.nodeLabels.placement":"[H_LEFT, V_TOP, OUTSIDE]","org.eclipse.elk.portConstraints":"FIXED_ORDER"},"ports":[{"height":8.0,"id":"P45","layoutOptions":{"org.eclipse.elk.port.index":"0","org.eclipse.elk.port.side":"WEST"},"width":8.0,"x":-8.0,"y":1.5999999999999996},{"height":8.0,"id":"P46","layoutOptions":{"org.eclipse.elk.port.index":"1","org.eclipse.elk.port.side":"EAST"},"width":8.0,"x":60.0,"y":16.0},{"height":8.0,"id":"P47","layoutOptions":{"org.eclipse.elk.port.index":"-2","org.eclipse.elk.port.side":"WEST"},"width":8.0,"x":-8.0,"y":11.2},{"height":8.0,"id":"P48","layoutOptions":{"org.eclipse.elk.port.index":"-3","org.eclipse.elk.port.side":"WEST"},"width":8.0,"x":-8.0,"y":20.799999999999997},{"height":8.0,"id":"P49","layoutOptions":{"org.eclipse.elk.port.index":"-4","org.eclipse.elk.port.side":"WEST"},"width":8.0,"x":-8.0,"y":30.4}],"width":60.0,"x":249.0,"y":93.1},{"height":46.0,"id":"N23","labels":[{"height":15.0,"id":"L23","text":"Scale","width":34.0,"x":0.0,"y":-20.0}],"layoutOptions":{"org.eclipse.elk.nodeLabels.placement":"[H_LEFT, V_TOP, OUTSIDE]","org.eclipse.elk.portConstraints":"FIXED_ORDER"},"ports":[{"height":8.0,"id":"P50","layoutOptions":{"org.eclipse.elk.port.index":"0","org.eclipse.elk.port.side":"WEST"},"width":8.0,"x":-8.0,"y":19.0},{"height":8.0,"id":"P51","layoutOptions":{"org.eclipse.elk.port.index":"1","org.eclipse.elk.port.side":"EAST"},"width":8.0,"x":66.0,"y":19.0}],"width":66.0,"x":20.0,"y":104.5},{"height":31.0,"id":"N24","labels":[{"height":15.0,"id":"L24","text":"ArrayToElements","width":99.0,"x":0.0,"y":-20.0}],"layoutOptions":{"org.eclipse.elk.nodeLabels.placement":"[H_LEFT, V_TOP, OUTSIDE]","org.eclipse.elk.portConstraints":"FIXED_ORDER"},"ports":[{"height":8.0,"id":"P52","layoutOptions":{"org.eclipse.elk.port.index":"0","org.eclipse.elk.port.side":"WEST"},"width":8.0,"x":-8.0,"y":11.5},{"height":8.0,"id":"P53","layoutOptions":{"org.eclipse.elk.port.index":"1","org.eclipse.elk.port.side":"EAST"},"width":8.0,"x":31.0,"y":11.5}],"width":31.0,"x":122.0,"y":112.0}],"edges":[{"container":"N20","id":"E27","sources":["P42"],"targets":["P50"]},{"container":"N20","id":"E28","sections":[{"bendPoints":[{"x":231.0,"y":52.0},{"x":231.0,"y":98.69999999999999}],"endPoint":{"x":241.0,"y":98.69999999999999},"id":"E28_s0","incomingShape":"P44","outgoingShape":"P45","startPoint":{"x":182.0,"y":52.0}}],"sources":["P44"],"targets":["P45"]},{"container":"N20","id":"E29","sources":["P46"],"targets":["P43"]},{"container":"N20","id":"E30","sections":[{"endPoint":{"x":114.0,"y":127.5},"id":"E30_s0","incomingShape":"P51","outgoingShape":"P52","startPoint":{"x":94.0,"y":127.5}}],"sources":["P51"],"targets":["P52"]},{"container":"N20","id":"E31","sections":[{"endPoint":{"x":241.0,"y":127.5},"id":"E31_s0","incomingShape":"P53","outgoingShape":"P49","startPoint":{"x":161.0,"y":127.5}}],"sources":["P53"],"targets":["P49"]},{"container":"N20","id":"E32","junctionPoints":[{"x":231.0,"y":127.5},{"x":231.0,"y":117.89999999999999}],"sections":[{"bendPoints":[{"x":231.0,"y":127.5},{"x":231.0,"y":117.89999999999999}],"endPoint":{"x":241.0,"y":117.89999999999999},"id":"E32_s0","incomingShape":"P53","outgoingShape":"P48","startPoint":{"x":161.0,"y":127.5}}],"sources":["P53"],"targets":["P48"]},{"container":"N20","id":"E33","sections":[{"bendPoints":[{"x":231.0,"y":127.5},{"x":231.0,"y":108.3}],"endPoint":{"x":241.0,"y":108.3},"id":"E33_s0","incomingShape":"P53","outgoingShape":"P47","startPoint":{"x":161.0,"y":127.5}}],"sources":["P53"],"targets":["P47"]}],"height":162.5,"id":"N20","labels":[{"height":15.0,"id":"L20","text":"MultiInstanceComposite","width":140.0,"x":0.0,"y":-20.0}],"layoutOptions":{"org.eclipse.elk.nodeLabels.placement":"[H_LEFT, V_TOP, OUTSIDE]","org.eclipse.elk.portConstraints":"FREE"},"ports":[{"height":8.0,"id":"P42","layoutOptions":{"org.eclipse.elk.port.index":"0","org.eclipse.elk.port.side":"WEST"},"width":8.0,"x":-8.0,"y":77.25},{"height":8.0,"id":"P43","layoutOptions":{"org.eclipse.elk.port.index":"1","org.eclipse.elk.port.side":"EAST"},"width":8.0,"x":331.0,"y":77.25}],"width":331.0,"x":147.0,"y":32.0}],"edges":[{"container":"N17","id":"E24","sources":["P38"],"targets":["P40"]},{"container":"N17","id":"E25","sections":[{"endPoint":{"x":139.0,"y":113.25},"id":"E25_s0","incomingShape":"P41","outgoingShape":"P42","startPoint":{"x":59.0,"y":113.25}}],"sources":["P41"],"targets":["P42"]},{"container":"N17","id":"E26","sections":[{"endPoint":{"x":506.0,"y":113.25},"id":"E26_s0","incomingShape":"P43","outgoingShape":"P39","startPoint":{"x":486.0,"y":113.25}}],"sources":["P43"],"targets":["P39"]}],"height":206.5,"id":"N17","labels":[{"height":15.0,"id":"L17","text":"Animate","width":49.0,"x":0.0,"y":-20.0}],"layoutOptions":{"org.eclipse.elk.nodeLabels.placement":"[H_LEFT, V_TOP, OUTSIDE]","org.eclipse.elk.portConstraints":"FREE"},"ports":[{"height":8.0,"id":"P38","layoutOptions":{"org.eclipse.elk.port.index":"0","org.eclipse.elk.port.side":"WEST"},"width":8.0,"x":-8.0,"y":99.25}],"width":612.0,"x":1815.0,"y":93.80555555555554},{"height":31.0,"id":"N25","labels":[{"height":15.0,"id":"L25","text":"ElementsToArray","width":99.0,"x":0.0,"y":-20.0}],"layoutOptions":{"org.eclipse.elk.nodeLabels.placement":"[H_LEFT, V_TOP, OUTSIDE]","org.eclipse.elk.portConstraints":"FIXED_ORDER"},"ports":[{"height":8.0,"id":"P54","layoutOptions":{"org.eclipse.elk.port.index":"0","org.eclipse.elk.port.side":"WEST"},"width":8.0,"x":-8.0,"y":11.5},{"height":8.0,"id":"P55","layoutOptions":{"org.eclipse.elk.port.index":"1","org.eclipse.elk.port.side":"EAST"},"width":8.0,"x":31.0,"y":11.5}],"width":31.0,"x":1549.0,"y":181.55555555555554}],"edges":[{"container":"G1","id":"E1","sections":[{"endPoint":{"x":1541.0,"y":197.05555555555554},"id":"E1_s0","incomingShape":"P2","outgoingShape":"P54","startPoint":{"x":1521.0,"y":197.05555555555554}}],"sources":["P2"],"targets":["P54"]},{"container":"G1","id":"E2","junctionPoints":[{"x":1797.0,"y":197.05555555555554}],"sections":[{"bendPoints":[{"x":1797.0,"y":197.05555555555554},{"x":1797.0,"y":112.52777777777777}],"endPoint":{"x":1521.0,"y":112.52777777777777},"id":"E2_s0","incomingShape":"P37","outgoingShape":"P1","startPoint":{"x":1787.0,"y":197.05555555555554}}],"sources":["P37"],"targets":["P1"]},{"container":"G1","id":"E3","sections":[{"endPoint":{"x":1807.0,"y":197.05555555555554},"id":"E3_s0","incomingShape":"P37","outgoingShape":"P38","startPoint":{"x":1787.0,"y":197.05555555555554}}],"sources":["P37"],"targets":["P38"]},{"container":"G1","id":"E4","sections":[{"endPoint":{"x":1668.0,"y":197.05555555555554},"id":"E4_s0","incomingShape":"P55","outgoingShape":"P36","startPoint":{"x":1588.0,"y":197.05555555555554}}],"sources":["P55"],"targets":["P36"]}],"height":312.30555555555554,"id":"G1","layoutOptions":{"org.eclipse.elk.portConstraints":"FREE","org.eclipse.elk.randomSeed":"1"},"width":2439.0,"x":0.0,"y":0.0}