{"children":[{"children":[{"height":0.0,"id":"N1","layoutOptions":{"org.eclipse.elk.nodeLabels.placement":"[H_CENTER, V_CENTER, INSIDE]","org.eclipse.elk.portConstraints":"FIXED_SIDE","org.eclipse.elk.portLabels.placement":"[OUTSIDE, NEXT_TO_PORT_IF_POSSIBLE]"},"ports":[{"height":7.0,"id":"P1","layoutOptions":{"org.eclipse.elk.port.side":"WEST"},"width":31.0,"x":-31.0,"y":0.0},{"height":7.0,"id":"P2_","layoutOptions":{"org.eclipse.elk.port.side":"WEST"},"width":27.0,"x":-27.0,"y":7.0}],"width":0.0,"x":43.0,"y":12.0}],"height":38.0,"id":"Down","layoutOptions":{"org.eclipse.elk.direction":"DOWN","org.eclipse.elk.nodeLabels.placement":"[H_CENTER, V_TOP, INSIDE]"},"width":55.0,"x":12.0,"y":12.0},{"children":[{"height":0.0,"id":"N1_g889107","layoutOptions":{"org.eclipse.elk.nodeLabels.placement":"[H_CENTER, V_CENTER, INSIDE]","org.eclipse.elk.portConstraints":"FIXED_SIDE","org.eclipse.elk.portLabels.placement":"[OUTSIDE, NEXT_TO_PORT_IF_POSSIBLE]"},"ports":[{"height":7.0,"id":"P1_g887202","layoutOptions":{"org.eclipse.elk.port.side":"WEST"},"width":31.0,"x":-31.0,"y":-7.0},{"height":7.0,"id":"P2__g548518","layoutOptions":{"org.eclipse.elk.port.side":"WEST"},"width":27.0,"x":-27.0,"y":-14.0}],"width":0.0,"x":43.0,"y":26.0}],"height":38.0,"id":"Up","layoutOptions":{"org.eclipse.elk.direction":"UP","org.eclipse.elk.nodeLabels.placement":"[H_CENTER, V_TOP, INSIDE]"},"width":55.0,"x":87.0,"y":12.0},{"children":[{"height":0.0,"id":"N1_g364569","layoutOptions":{"org.eclipse.elk.nodeLabels.placement":"[H_CENTER, V_CENTER, INSIDE]","org.eclipse.elk.portConstraints":"FIXED_SIDE","org.eclipse.elk.portLabels.placement":"[OUTSIDE, NEXT_TO_PORT_IF_POSSIBLE]"},"ports":[{"height":7.0,"id":"P1_g740936","layoutOptions":{"org.eclipse.elk.port.side":"WEST"},"width":31.0,"x":-31.0,"y":0.0},{"height":7.0,"id":"P2__g924082","layoutOptions":{"org.eclipse.elk.port.side":"WEST"},"width":27.0,"x":-27.0,"y":7.0}],"width":0.0,"x":43.0,"y":12.0}],"height":38.0,"id":"Left","layoutOptions":{"org.eclipse.elk.direction":"LEFT","org.eclipse.elk.nodeLabels.placement":"[H_CENTER, V_TOP, INSIDE]"},"width":55.0,"x":12.0,"y":70.0},{"children":[{"height":0.0,"id":"N1_g895710","layoutOptions":{"org.eclipse.elk.nodeLabels.placement":"[H_CENTER, V_CENTER, INSIDE]","org.eclipse.elk.portConstraints":"FIXED_SIDE","org.eclipse.elk.portLabels.placement":"[OUTSIDE, NEXT_TO_PORT_IF_POSSIBLE]"},"ports":[{"height":7.0,"id":"P1_g189873","layoutOptions":{"org.eclipse.elk.port.side":"WEST"},"width":31.0,"x":-31.0,"y":7.0},{"height":7.0,"id":"P2__g431627","layoutOptions":{"org.eclipse.elk.port.side":"WEST"},"width":27.0,"x":-27.0,"y":0.0}],"width":0.0,"x":43.0,"y":12.0}],"height":38.0,"id":"Right","layoutOptions":{"org.eclipse.elk.direction":"RIGHT","org.eclipse.elk.nodeLabels.placement":"[H_CENTER, V_TOP, INSIDE]"},"width":55.0,"x":87.0,"y":70.0}],"height":120.0,"id":"n0","layoutOptions":{"org.eclipse.elk.randomSeed":"1"},"width":154.0,"x":0.0,"y":0.0}